emailev-1.0.0.dist-info/licenses/License
emailev_tool/__init__.py
emailev_tool/email_generator.py
emailev_tool/email_validator.py
emailev_tool/hibp_checker.py
emailev_tool/main.py
emailev_tool/proxy_manager.py
emailev_tool/pyhunter_integration.py
emailev_tool/reputation_checker.py
emailev_tool/tor_manager.py
emailev_tool/utils.py
emailev-1.0.0.dist-info/METADATA
emailev-1.0.0.dist-info/WHEEL
emailev-1.0.0.dist-info/entry_points.txt
emailev-1.0.0.dist-info/top_level.txt
emailev-1.0.0.dist-info/RECORD
